MANIFEST.in
README.md
setup.py
code2chart.egg-info/PKG-INFO
code2chart.egg-info/SOURCES.txt
code2chart.egg-info/dependency_links.txt
code2chart.egg-info/requires.txt
code2chart.egg-info/top_level.txt
code2flowchart/__init__.py
code2flowchart/config.json
code2flowchart/constants.py
code2flowchart/example.py
code2flowchart/flowchart.png
code2flowchart/generators.py
code2flowchart/github-code-extractor.py
code2flowchart/main.py
code2flowchart/__pycache__/__init__.cpython-311.pyc
code2flowchart/__pycache__/constants.cpython-311.pyc
code2flowchart/agents/__init__.py
code2flowchart/code2flowchart.egg-info/PKG-INFO
code2flowchart/code2flowchart.egg-info/SOURCES.txt
code2flowchart/code2flowchart.egg-info/dependency_links.txt
code2flowchart/code2flowchart.egg-info/requires.txt
code2flowchart/code2flowchart.egg-info/top_level.txt
code2flowchart/dist/code2flowchart-0.1.0-py3-none-any.whl
code2flowchart/dist/code2flowchart-0.1.0.tar.gz
code2flowchart/templates/__init__.py
code2flowchart/templates/flowchart_prompt.py
code2flowchart/templates/prompt.py
code2flowchart/templates/__pycache__/__init__.cpython-311.pyc
code2flowchart/templates/__pycache__/flowchart_prompt.cpython-311.pyc
code2flowchart/templates/__pycache__/prompt.cpython-311.pyc
code2flowchart/tools/Bash.py
code2flowchart/tools/CodeExplanationTool.py
code2flowchart/tools/FlowchartGenTool.py
code2flowchart/tools/__init__.py
code2flowchart/tools/__pycache__/CodeExplanationTool.cpython-311.pyc
code2flowchart/tools/__pycache__/FlowchartGenTool.cpython-311.pyc
code2flowchart/tools/__pycache__/__init__.cpython-311.pyc
code2flowchart/utils/__init__.py
code2flowchart/utils/mermaid.py
code2flowchart/utils/__pycache__/__init__.cpython-311.pyc
code2flowchart/utils/__pycache__/mermaid.cpython-311.pyc
code2flowchart/utils/asyncllm/AbstractAsyncLLM.py
code2flowchart/utils/asyncllm/AsyncLLM.py
code2flowchart/utils/asyncllm/__init__.py
code2flowchart/utils/asyncllm/helpers.py