Metadata-Version: 2.1
Name: code2chart
Version: 0.1.0
Summary: Transform your code to a simple explanatory flowchart.
Home-page: UNKNOWN
Author: Iyadh Khalfallah
License: MIT
Platform: UNKNOWN
